MANIFEST.in
README.md
pyproject.toml
setup.py
./requirements/requirements.txt
./requirements/test_requirements.txt
mosaic_minerals_model/VERSION
mosaic_minerals_model/__init__.py
mosaic_minerals_model/config.yml
mosaic_minerals_model/pipeline.py
mosaic_minerals_model/predict.py
mosaic_minerals_model/train_pipeline.py
mosaic_minerals_model.egg-info/PKG-INFO
mosaic_minerals_model.egg-info/SOURCES.txt
mosaic_minerals_model.egg-info/dependency_links.txt
mosaic_minerals_model.egg-info/requires.txt
mosaic_minerals_model.egg-info/top_level.txt
mosaic_minerals_model/config/__init__.py
mosaic_minerals_model/config/core.py
mosaic_minerals_model/datasets/__init__.py
mosaic_minerals_model/datasets/test.csv
mosaic_minerals_model/datasets/train.csv
mosaic_minerals_model/processing/__init__.py
mosaic_minerals_model/processing/data_manager.py
mosaic_minerals_model/processing/features.py
mosaic_minerals_model/processing/validation.py
mosaic_minerals_model/trained_models/__init__.py
mosaic_minerals_model/trained_models/mosaic_minerals_output_v0.0.1.pkl