Metadata-Version: 2.1
Name: mosaic-minerals-model
Version: 0.0.1
Summary: 3D Prospectivity for Mosaic_Minerals
Home-page: https://github.com/ozerozdal/Mosaic_Minerals
Author: OzerOzdal
Author-email: ozer.ozdal@goldspot.ca
License: BSD-3
Platform: UNKNOWN
Classifier: License :: OSI Approved :: MIT License
Classifier: Programming Language :: Python
Classifier: Programming Language :: Python :: 3
Classifier: Programming Language :: Python :: 3.6
Classifier: Programming Language :: Python :: 3.7
Classifier: Programming Language :: Python :: 3.8
Classifier: Programming Language :: Python :: 3.9
Classifier: Programming Language :: Python :: Implementation :: CPython
Classifier: Programming Language :: Python :: Implementation :: PyPy
Requires-Python: >=3.6.0
